<Shipment>
  <id type="integer">20</id>
  <delivery-date type="date">2015-11-10</delivery-date>
  <created-at type="dateTime">2015-11-10T00:41:02Z</created-at>
  <updated-at type="dateTime">2015-11-10T00:41:02Z</updated-at>
  <storage-number type="integer" nil="true"/>
  <products type="array">
    <product>
      <id type="integer">21</id>
      <description>p1</description>
      <value type="decimal">111.0</value>
      <shipment-id type="integer">20</shipment-id>
      <created-at type="dateTime">2015-11-10T00:41:02Z</created-at>
      <updated-at type="dateTime">2015-11-10T00:41:02Z</updated-at>
    </product>
  </products>
</Shipment>
